funtime/__init__.py
funtime/config.py
funtime/main.py
funtime/util/__init__.py
funtime/util/storage.py
funtime/util/ticker_handler.py
funtime/util/timing.py
funtime-0.4.7.dist-info/METADATA
funtime-0.4.7.dist-info/RECORD
funtime-0.4.7.dist-info/WHEEL
funtime-0.4.7.dist-info/top_level.txt
