Metadata-Version: 2.1
Name: funtime
Version: 0.4.7
Summary: A timeseries library to make your workflow easier
Home-page: UNKNOWN
Author: Kevin Hill
Author-email: kevin@funguana.com
License: UNKNOWN
Platform: UNKNOWN
Classifier: Programming Language :: Python :: 3
Classifier: License :: OSI Approved :: MIT License
Classifier: Operating System :: OS Independent
Requires-Dist: scipy
Requires-Dist: numpy
Requires-Dist: pandas
Requires-Dist: click
Requires-Dist: arctic
Requires-Dist: toolz
Requires-Dist: dask
Requires-Dist: cloudpickle
Requires-Dist: dask[complete]
Requires-Dist: dask[dataframe]
Requires-Dist: python-decouple
Requires-Dist: maya
Requires-Dist: crayons
